mirapi/__init__.py
mirapi/errors.py
mirapi/exceptions.py
mirapi/mirapi.py
mirapi/requests.py
mirapi/responses.py
mirapi/router.py
mirapi/types.py
mirapi-0.0.3.dist-info/LICENSE
mirapi-0.0.3.dist-info/METADATA
mirapi-0.0.3.dist-info/WHEEL
mirapi-0.0.3.dist-info/top_level.txt
mirapi-0.0.3.dist-info/RECORD
