Metadata-Version: 2.1
Name: mirapi
Version: 0.0.3
Summary: A lightweight and fast ASGI-based Python web framework for building APIs with automatic OpenAPI documentation.
Home-page: https://github.com/Diyarbekoralbaev/mirapi
Author: Diyarbek Oralbaev
Author-email: diyarbekdev@gmail.com
License: MIT
Classifier: License :: OSI Approved :: MIT License
Classifier: Programming Language :: Python
Classifier: Programming Language :: Python :: 3
Classifier: Programming Language :: Python :: 3.9
Classifier: Programming Language :: Python :: 3.10
Classifier: Programming Language :: Python :: 3.11
Classifier: Programming Language :: Python :: 3.12
Classifier: Programming Language :: Python :: Implementation :: CPython
Classifier: Programming Language :: Python :: Implementation :: PyPy
Classifier: Development Status :: 3 - Alpha
Classifier: Operating System :: OS Independent
Classifier: Topic :: Internet :: WWW/HTTP
Classifier: Framework :: AsyncIO
Classifier: Intended Audience :: Developers
Requires-Python: >=3.9.0
License-File: LICENSE
Requires-Dist: starlette==0.39.2
Requires-Dist: parse==1.20.2
Requires-Dist: uvicorn==0.31.1
Requires-Dist: pydantic==2.9.2
Provides-Extra: database
Requires-Dist: psycopg2-binary; extra == "database"
Provides-Extra: orm
Requires-Dist: sqlalchemy; extra == "orm"
